djangoldp_editor/__init__.py
djangoldp_editor/admin.py
djangoldp_editor/apps.py
djangoldp_editor/factories.py
djangoldp_editor/models.py
djangoldp_editor/translation.py
djangoldp_editor/management/__init__.py
djangoldp_editor/management/commands/__init__.py
djangoldp_editor/management/commands/mock_example.py
djangoldp_editor/migrations/0001_initial.py
djangoldp_editor/migrations/0002_helloworld.py
djangoldp_editor/migrations/0003_users.py
djangoldp_editor/migrations/0004_auto_20191212_1453.py
djangoldp_editor/migrations/0005_auto_20191212_1454.py
djangoldp_editor/migrations/0006_auto_20191212_1510.py
djangoldp_editor/migrations/0007_auto_20191218_1033.py
djangoldp_editor/migrations/0008_auto_20201008_1430.py
djangoldp_editor/migrations/0009_auto_20211115_1449.py
djangoldp_editor/migrations/0010_auto_20211115_1502.py
djangoldp_editor/migrations/__init__.py
djangoldp_editor-1.1.0.dist-info/METADATA
djangoldp_editor-1.1.0.dist-info/WHEEL
djangoldp_editor-1.1.0.dist-info/top_level.txt
djangoldp_editor-1.1.0.dist-info/RECORD
