Metadata-Version: 2.1
Name: djangoldp-editor
Version: 1.1.0
Summary: DjangoLDP Editor
Home-page: http://git.happy-dev.fr/startinblox/djangoldp-packages/djangoldp-editor
Author: Startin'blox
Author-email: alice@startinblox.com
License: MIT
Platform: UNKNOWN
Classifier: Programming Language :: Python :: 3
Requires-Dist: djangoldp (>=1.0.0)
